Metadata-Version: 1.1
Name: OptimizationTools
Version: 0.0.1
Summary: Optimization of functions and Linear system solving
Home-page: UNKNOWN
Author: Ahmed Mrabet
Author-email: ahmedmrabet.002@gmail.com
License: MIT
Keywords: Optimization
Platform: UNKNOWN
Classifier: Development Status :: 5 - Production/Stable
Classifier: Intended Audience :: Education
Classifier: License :: OSI Approved :: MIT License
Classifier: Operating System :: Unix
Classifier: Programming Language :: Python :: 3.9
